cwitools/__init__.py
cwitools/config.py
cwitools/coordinates.py
cwitools/extraction.py
cwitools/measurement.py
cwitools/modeling.py
cwitools/synthesis.py
cwitools/utils.py
cwitools/data/gal_lines/drewchojnowski_geldata.csv
cwitools/data/sky/keck_lines.txt
cwitools/data/sky/palomar_lines.txt
cwitools/reduction/__init__.py
cwitools/reduction/cubes.py
cwitools/reduction/units.py
cwitools/reduction/variance.py
cwitools/reduction/wcs.py
cwitools/scripts/__init__.py
cwitools/scripts/apply_mask.py
cwitools/scripts/apply_wcs.py
cwitools/scripts/asmooth.py
cwitools/scripts/bg_sub.py
cwitools/scripts/coadd.py
cwitools/scripts/crop.py
cwitools/scripts/fit_covar.py
cwitools/scripts/get_mask.py
cwitools/scripts/get_nb.py
cwitools/scripts/get_rprof.py
cwitools/scripts/get_var.py
cwitools/scripts/get_wl.py
cwitools/scripts/mask_z.py
cwitools/scripts/measure_wcs.py
cwitools/scripts/obj_lum.py
cwitools/scripts/obj_morpho.py
cwitools/scripts/obj_sb.py
cwitools/scripts/obj_spec.py
cwitools/scripts/obj_zfit.py
cwitools/scripts/obj_zmoments.py
cwitools/scripts/psf_sub.py
cwitools/scripts/rebin.py
cwitools/scripts/scale_var.py
cwitools/scripts/segment.py
cwitools/scripts/slice_corr.py
cwitools-0.8.7.dist-info/LICENSE
cwitools-0.8.7.dist-info/METADATA
cwitools-0.8.7.dist-info/WHEEL
cwitools-0.8.7.dist-info/entry_points.txt
cwitools-0.8.7.dist-info/top_level.txt
cwitools-0.8.7.dist-info/RECORD
