Metadata-Version: 2.1
Name: cwitools
Version: 0.8.7
Summary: Analysis and Reduction Tools for PCWI/KCWI Data
Home-page: https://github.com/dbosul/cwitools
Author: Donal O'Sullivan
Author-email: dosulliv@caltech.edu
License: UNKNOWN
Download-URL: https://github.com/dbosul/cwitools/archive/v0.8.2.tar.gz
Platform: UNKNOWN
Requires-Dist: PyAstronomy
Requires-Dist: argparse
Requires-Dist: astropy
Requires-Dist: matplotlib
Requires-Dist: numpy
Requires-Dist: photutils
Requires-Dist: pyregion
Requires-Dist: reproject
Requires-Dist: scikit-image
Requires-Dist: scipy
Requires-Dist: shapely
Requires-Dist: tqdm
